{
    "qubits": {
        "q1": {
            "id": "q1",
            "xy": {
                "operations": {
                    "x180_DragCosine": {
                        "length": 16,
                        "digital_marker": "ON",
                        "axis_angle": 0,
                        "amplitude": 0.16342947701568272,
                        "alpha": -1.3101266496425672,
                        "anharmonicity": "#/qubits/q1/anharmonicity",
                        "detuning": -4520000.0,
                        "__class__": "quam.components.pulses.DragCosinePulse"
                    },
                    "x90_DragCosine": {
                        "length": "#../x180_DragCosine/length",
                        "digital_marker": "ON",
                        "axis_angle": 0,
                        "amplitude": 0.08171473850784136,
                        "alpha": -0.8001,
                        "anharmonicity": "#../x180_DragCosine/anharmonicity",
                        "__class__": "quam.components.pulses.DragCosinePulse"
                    },
                    "-x90_DragCosine": {
                        "length": "#../x180_DragCosine/length",
                        "digital_marker": "ON",
                        "axis_angle": 3.141592653589793,
                        "amplitude": "#../x90_DragCosine/amplitude",
                        "alpha": "#../x90_DragCosine/alpha",
                        "anharmonicity": "#../x180_DragCosine/anharmonicity",
                        "detuning": "#../x180_DragCosine/detuning",
                        "__class__": "quam.components.pulses.DragCosinePulse"
                    },
                    "y180_DragCosine": {
                        "length": "#../x180_DragCosine/length",
                        "digital_marker": "ON",
                        "axis_angle": 1.5707963267948966,
                        "amplitude": "#../x180_DragCosine/amplitude",
                        "alpha": "#../x180_DragCosine/alpha",
                        "anharmonicity": "#../x180_DragCosine/anharmonicity",
                        "detuning": "#../x180_DragCosine/detuning",
                        "__class__": "quam.components.pulses.DragCosinePulse"
                    },
                    "y90_DragCosine": {
                        "length": "#../x180_DragCosine/length",
                        "digital_marker": "ON",
                        "axis_angle": 1.5707963267948966,
                        "amplitude": "#../x90_DragCosine/amplitude",
                        "alpha": "#../x90_DragCosine/alpha",
                        "anharmonicity": "#../x180_DragCosine/anharmonicity",
                        "detuning": "#../x90_DragCosine/detuning",
                        "__class__": "quam.components.pulses.DragCosinePulse"
                    },
                    "-y90_DragCosine": {
                        "length": "#../x180_DragCosine/length",
                        "digital_marker": "ON",
                        "axis_angle": -1.5707963267948966,
                        "amplitude": "#../x90_DragCosine/amplitude",
                        "alpha": "#../x90_DragCosine/alpha",
                        "anharmonicity": "#../x180_DragCosine/anharmonicity",
                        "detuning": "#../x90_DragCosine/detuning",
                        "__class__": "quam.components.pulses.DragCosinePulse"
                    },
                    "x180_Square": {
                        "length": 40,
                        "digital_marker": "ON",
                        "amplitude": 0.1,
                        "axis_angle": 0,
                        "__class__": "quam.components.pulses.SquarePulse"
                    },
                    "x90_Square": {
                        "length": "#../x180_Square/length",
                        "digital_marker": "ON",
                        "amplitude": 0.05,
                        "axis_angle": 0,
                        "__class__": "quam.components.pulses.SquarePulse"
                    },
                    "-x90_Square": {
                        "length": "#../x180_Square/length",
                        "digital_marker": "ON",
                        "amplitude": -0.125,
                        "axis_angle": 0,
                        "__class__": "quam.components.pulses.SquarePulse"
                    },
                    "y180_Square": {
                        "length": "#../x180_Square/length",
                        "digital_marker": "ON",
                        "amplitude": 0.25,
                        "axis_angle": 90,
                        "__class__": "quam.components.pulses.SquarePulse"
                    },
                    "y90_Square": {
                        "length": "#../x180_Square/length",
                        "digital_marker": "ON",
                        "amplitude": 0.125,
                        "axis_angle": 90,
                        "__class__": "quam.components.pulses.SquarePulse"
                    },
                    "-y90_Square": {
                        "length": "#../x180_Square/length",
                        "digital_marker": "ON",
                        "amplitude": -0.125,
                        "axis_angle": 90,
                        "__class__": "quam.components.pulses.SquarePulse"
                    },
                    "x180": "#./x180_DragCosine",
                    "x90": "#./x90_DragCosine",
                    "-x90": "#./-x90_DragCosine",
                    "y180": "#./y180_DragCosine",
                    "y90": "#./y90_DragCosine",
                    "-y90": "#./-y90_DragCosine",
                    "saturation": {
                        "length": 20000,
                        "digital_marker": "ON",
                        "amplitude": 0.5,
                        "axis_angle": 0,
                        "__class__": "quam.components.pulses.SquarePulse"
                    },
                    "EF_x180": {
                        "length": 16,
                        "digital_marker": "ON",
                        "axis_angle": 0,
                        "amplitude": 0.11313255695036671,
                        "alpha": -1.0,
                        "anharmonicity": 206000000,
                        "__class__": "quam.components.pulses.DragCosinePulse"
                    }
                },
                "intermediate_frequency": 208082149.59318766,
                "thread": "a",
                "opx_output": "#/wiring/qubits/q1/xy/opx_output",
                "__class__": "quam.components.channels.MWChannel"
            },
            "z": {
                "operations": {
                    "const": {
                        "length": 100,
                        "amplitude": 0.1,
                        "__class__": "quam.components.pulses.SquarePulse"
                    }
                },
                "opx_output": "#/wiring/qubits/q1/z/opx_output",
                "independent_offset": 0.0963340645087207,
                "min_offset": 0.45
            },
            "resonator": {
                "depletion_time": 1000,
                "confusion_matrix": [
                    [
                        0.975,
                        0.025
                    ],
                    [
                        0.0905,
                        0.9095
                    ]
                ],
                "operations": {
                    "readout": {
                        "length": 2000,
                        "amplitude": 0.10254241381679749,
                        "threshold": -3.326815539983481e-05,
                        "rus_exit_threshold": -0.00020092649227884318,
                        "integration_weights_angle": -8.10650716998602,
                        "__class__": "quam.components.pulses.SquareReadoutPulse"
                    },
                    "const": {
                        "length": 100,
                        "amplitude": 0.125,
                        "__class__": "quam.components.pulses.SquarePulse"
                    }
                },
                "intermediate_frequency": -16682781.0,
                "thread": "a",
                "opx_input": "#/wiring/qubits/q1/rr/opx_input",
                "time_of_flight": 28,
                "opx_output": "#/wiring/qubits/q1/rr/opx_output",
                "__class__": "quam_libs.components.readout_resonator.ReadoutResonatorMW"
            },
            "anharmonicity": 205600000,
            "freq_vs_flux_01_quad_term": -16301668240.305855,
            "T1": 27968,
            "T2ramsey": 2.461718327013627e-05,
            "thermalization_time_factor": 10,
            "phi0_current": 32.29567929529683,
            "phi0_voltage": 0.6459135859059366,
            "chi": -2610000.0,
            "grid_location": "0,0"
        },
        "q2": {
            "id": "q2",
            "xy": {
                "operations": {
                    "x180_DragCosine": {
                        "length": 16,
                        "digital_marker": "ON",
                        "axis_angle": 0,
                        "amplitude": 0.2476971481141532,
                        "alpha": -0.8027456502727682,
                        "anharmonicity": "#/qubits/q2/anharmonicity",
                        "__class__": "quam.components.pulses.DragCosinePulse"
                    },
                    "x90_DragCosine": {
                        "length": "#../x180_DragCosine/length",
                        "digital_marker": "ON",
                        "axis_angle": 0,
                        "amplitude": 0.1238485740570766,
                        "alpha": -0.643762466117261,
                        "anharmonicity": "#../x180_DragCosine/anharmonicity",
                        "detuning": -160000.0,
                        "__class__": "quam.components.pulses.DragCosinePulse"
                    },
                    "-x90_DragCosine": {
                        "length": "#../x180_DragCosine/length",
                        "digital_marker": "ON",
                        "axis_angle": 3.141592653589793,
                        "amplitude": "#../x90_DragCosine/amplitude",
                        "alpha": "#../x90_DragCosine/alpha",
                        "anharmonicity": "#../x180_DragCosine/anharmonicity",
                        "detuning": "#../x180_DragCosine/detuning",
                        "__class__": "quam.components.pulses.DragCosinePulse"
                    },
                    "y180_DragCosine": {
                        "length": "#../x180_DragCosine/length",
                        "digital_marker": "ON",
                        "axis_angle": 1.5707963267948966,
                        "amplitude": "#../x180_DragCosine/amplitude",
                        "alpha": "#../x180_DragCosine/alpha",
                        "anharmonicity": "#../x180_DragCosine/anharmonicity",
                        "detuning": "#../x180_DragCosine/detuning",
                        "__class__": "quam.components.pulses.DragCosinePulse"
                    },
                    "y90_DragCosine": {
                        "length": "#../x180_DragCosine/length",
                        "digital_marker": "ON",
                        "axis_angle": 1.5707963267948966,
                        "amplitude": "#../x90_DragCosine/amplitude",
                        "alpha": "#../x90_DragCosine/alpha",
                        "anharmonicity": "#../x180_DragCosine/anharmonicity",
                        "detuning": "#../x90_DragCosine/detuning",
                        "__class__": "quam.components.pulses.DragCosinePulse"
                    },
                    "-y90_DragCosine": {
                        "length": "#../x180_DragCosine/length",
                        "digital_marker": "ON",
                        "axis_angle": -1.5707963267948966,
                        "amplitude": "#../x90_DragCosine/amplitude",
                        "alpha": "#../x90_DragCosine/alpha",
                        "anharmonicity": "#../x180_DragCosine/anharmonicity",
                        "detuning": "#../x90_DragCosine/detuning",
                        "__class__": "quam.components.pulses.DragCosinePulse"
                    },
                    "x180_Square": {
                        "length": 40,
                        "digital_marker": "ON",
                        "amplitude": 0.1,
                        "axis_angle": 0,
                        "__class__": "quam.components.pulses.SquarePulse"
                    },
                    "x90_Square": {
                        "length": "#../x180_Square/length",
                        "digital_marker": "ON",
                        "amplitude": 0.05,
                        "axis_angle": 0,
                        "__class__": "quam.components.pulses.SquarePulse"
                    },
                    "-x90_Square": {
                        "length": "#../x180_Square/length",
                        "digital_marker": "ON",
                        "amplitude": -0.125,
                        "axis_angle": 0,
                        "__class__": "quam.components.pulses.SquarePulse"
                    },
                    "y180_Square": {
                        "length": "#../x180_Square/length",
                        "digital_marker": "ON",
                        "amplitude": 0.25,
                        "axis_angle": 90,
                        "__class__": "quam.components.pulses.SquarePulse"
                    },
                    "y90_Square": {
                        "length": "#../x180_Square/length",
                        "digital_marker": "ON",
                        "amplitude": 0.125,
                        "axis_angle": 90,
                        "__class__": "quam.components.pulses.SquarePulse"
                    },
                    "-y90_Square": {
                        "length": "#../x180_Square/length",
                        "digital_marker": "ON",
                        "amplitude": -0.125,
                        "axis_angle": 90,
                        "__class__": "quam.components.pulses.SquarePulse"
                    },
                    "x180": "#./x180_DragCosine",
                    "x90": "#./x90_DragCosine",
                    "-x90": "#./-x90_DragCosine",
                    "y180": "#./y180_DragCosine",
                    "y90": "#./y90_DragCosine",
                    "-y90": "#./-y90_DragCosine",
                    "saturation": {
                        "length": 20000,
                        "digital_marker": "ON",
                        "amplitude": 0.5,
                        "axis_angle": 0,
                        "__class__": "quam.components.pulses.SquarePulse"
                    },
                    "EF_x180": {
                        "length": 16,
                        "digital_marker": "ON",
                        "axis_angle": 0,
                        "amplitude": 0.1198980108261488,
                        "alpha": -1.0,
                        "anharmonicity": 211000000,
                        "__class__": "quam.components.pulses.DragCosinePulse"
                    }
                },
                "intermediate_frequency": -62905876.696792774,
                "thread": "b",
                "opx_output": "#/wiring/qubits/q2/xy/opx_output",
                "__class__": "quam.components.channels.MWChannel"
            },
            "z": {
                "operations": {
                    "const": {
                        "length": 100,
                        "amplitude": 0.1,
                        "__class__": "quam.components.pulses.SquarePulse"
                    }
                },
                "opx_output": "#/wiring/qubits/q2/z/opx_output",
                "independent_offset": 0.08462775458692756,
                "min_offset": 0.4
            },
            "resonator": {
                "depletion_time": 1000,
                "confusion_matrix": [
                    [
                        0.943,
                        0.057
                    ],
                    [
                        0.0945,
                        0.9055
                    ]
                ],
                "operations": {
                    "readout": {
                        "length": 2000,
                        "amplitude": 0.09539932459063855,
                        "threshold": 6.0161967339534926e-05,
                        "rus_exit_threshold": -1.9782466290951985e-05,
                        "integration_weights_angle": -0.4591216703454819,
                        "__class__": "quam.components.pulses.SquareReadoutPulse"
                    },
                    "const": {
                        "length": 100,
                        "amplitude": 0.125,
                        "__class__": "quam.components.pulses.SquarePulse"
                    }
                },
                "intermediate_frequency": 74074257.0,
                "thread": "b",
                "opx_input": "#/wiring/qubits/q2/rr/opx_input",
                "time_of_flight": 28,
                "opx_output": "#/wiring/qubits/q2/rr/opx_output",
                "__class__": "quam_libs.components.readout_resonator.ReadoutResonatorMW"
            },
            "anharmonicity": 209600000,
            "freq_vs_flux_01_quad_term": -16932361425.748524,
            "T1": 38232,
            "T2ramsey": 2.461718327013627e-05,
            "thermalization_time_factor": 10,
            "phi0_current": 27.86861559409129,
            "phi0_voltage": 0.5573723118818258,
            "chi": -1380000.0,
            "grid_location": "1,0"
        },
        "q3": {
            "id": "q3",
            "xy": {
                "operations": {
                    "x180_DragCosine": {
                        "length": 16,
                        "digital_marker": "ON",
                        "axis_angle": 0,
                        "amplitude": 0.1894764066016367,
                        "alpha": -0.9788104759175057,
                        "anharmonicity": "#/qubits/q3/anharmonicity",
                        "detuning": 320000.0,
                        "__class__": "quam.components.pulses.DragCosinePulse"
                    },
                    "x90_DragCosine": {
                        "length": "#../x180_DragCosine/length",
                        "digital_marker": "ON",
                        "axis_angle": 0,
                        "amplitude": 0.09473820330081835,
                        "alpha": -1.0008880545292445,
                        "anharmonicity": "#../x180_DragCosine/anharmonicity",
                        "__class__": "quam.components.pulses.DragCosinePulse"
                    },
                    "-x90_DragCosine": {
                        "length": "#../x180_DragCosine/length",
                        "digital_marker": "ON",
                        "axis_angle": 3.141592653589793,
                        "amplitude": "#../x90_DragCosine/amplitude",
                        "alpha": "#../x90_DragCosine/alpha",
                        "anharmonicity": "#../x180_DragCosine/anharmonicity",
                        "detuning": "#../x180_DragCosine/detuning",
                        "__class__": "quam.components.pulses.DragCosinePulse"
                    },
                    "y180_DragCosine": {
                        "length": "#../x180_DragCosine/length",
                        "digital_marker": "ON",
                        "axis_angle": 1.5707963267948966,
                        "amplitude": "#../x180_DragCosine/amplitude",
                        "alpha": "#../x180_DragCosine/alpha",
                        "anharmonicity": "#../x180_DragCosine/anharmonicity",
                        "detuning": "#../x180_DragCosine/detuning",
                        "__class__": "quam.components.pulses.DragCosinePulse"
                    },
                    "y90_DragCosine": {
                        "length": "#../x180_DragCosine/length",
                        "digital_marker": "ON",
                        "axis_angle": 1.5707963267948966,
                        "amplitude": "#../x90_DragCosine/amplitude",
                        "alpha": "#../x90_DragCosine/alpha",
                        "anharmonicity": "#../x180_DragCosine/anharmonicity",
                        "detuning": "#../x90_DragCosine/detuning",
                        "__class__": "quam.components.pulses.DragCosinePulse"
                    },
                    "-y90_DragCosine": {
                        "length": "#../x180_DragCosine/length",
                        "digital_marker": "ON",
                        "axis_angle": -1.5707963267948966,
                        "amplitude": "#../x90_DragCosine/amplitude",
                        "alpha": "#../x90_DragCosine/alpha",
                        "anharmonicity": "#../x180_DragCosine/anharmonicity",
                        "detuning": "#../x90_DragCosine/detuning",
                        "__class__": "quam.components.pulses.DragCosinePulse"
                    },
                    "x180_Square": {
                        "length": 40,
                        "digital_marker": "ON",
                        "amplitude": 0.1,
                        "axis_angle": 0,
                        "__class__": "quam.components.pulses.SquarePulse"
                    },
                    "x90_Square": {
                        "length": "#../x180_Square/length",
                        "digital_marker": "ON",
                        "amplitude": 0.05,
                        "axis_angle": 0,
                        "__class__": "quam.components.pulses.SquarePulse"
                    },
                    "-x90_Square": {
                        "length": "#../x180_Square/length",
                        "digital_marker": "ON",
                        "amplitude": -0.125,
                        "axis_angle": 0,
                        "__class__": "quam.components.pulses.SquarePulse"
                    },
                    "y180_Square": {
                        "length": "#../x180_Square/length",
                        "digital_marker": "ON",
                        "amplitude": 0.25,
                        "axis_angle": 90,
                        "__class__": "quam.components.pulses.SquarePulse"
                    },
                    "y90_Square": {
                        "length": "#../x180_Square/length",
                        "digital_marker": "ON",
                        "amplitude": 0.125,
                        "axis_angle": 90,
                        "__class__": "quam.components.pulses.SquarePulse"
                    },
                    "-y90_Square": {
                        "length": "#../x180_Square/length",
                        "digital_marker": "ON",
                        "amplitude": -0.125,
                        "axis_angle": 90,
                        "__class__": "quam.components.pulses.SquarePulse"
                    },
                    "x180": "#./x180_DragCosine",
                    "x90": "#./x90_DragCosine",
                    "-x90": "#./-x90_DragCosine",
                    "y180": "#./y180_DragCosine",
                    "y90": "#./y90_DragCosine",
                    "-y90": "#./-y90_DragCosine",
                    "saturation": {
                        "length": 20000,
                        "digital_marker": "ON",
                        "amplitude": 0.5,
                        "axis_angle": 0,
                        "__class__": "quam.components.pulses.SquarePulse"
                    },
                    "EF_x180": {
                        "length": 16,
                        "digital_marker": "ON",
                        "axis_angle": 0,
                        "amplitude": 0.09511977433456727,
                        "alpha": 0.0,
                        "anharmonicity": 203000000,
                        "__class__": "quam.components.pulses.DragCosinePulse"
                    }
                },
                "intermediate_frequency": 248454058.1288513,
                "thread": "c",
                "opx_output": "#/wiring/qubits/q3/xy/opx_output",
                "__class__": "quam.components.channels.MWChannel"
            },
            "z": {
                "operations": {
                    "const": {
                        "length": 100,
                        "amplitude": 0.1,
                        "__class__": "quam.components.pulses.SquarePulse"
                    }
                },
                "opx_output": "#/wiring/qubits/q3/z/opx_output",
                "independent_offset": 0.11694288952645328
            },
            "resonator": {
                "depletion_time": 1000,
                "confusion_matrix": [
                    [
                        0.9695,
                        0.0305
                    ],
                    [
                        0.0925,
                        0.9075
                    ]
                ],
                "operations": {
                    "readout": {
                        "length": 2000,
                        "amplitude": 0.14209886620943551,
                        "threshold": -9.70013334519735e-06,
                        "rus_exit_threshold": -9.253055894712506e-05,
                        "integration_weights_angle": -18.23990904774417,
                        "__class__": "quam.components.pulses.SquareReadoutPulse"
                    },
                    "const": {
                        "length": 100,
                        "amplitude": 0.125,
                        "__class__": "quam.components.pulses.SquarePulse"
                    }
                },
                "intermediate_frequency": -83173877.0,
                "thread": "c",
                "opx_input": "#/wiring/qubits/q3/rr/opx_input",
                "time_of_flight": 28,
                "opx_output": "#/wiring/qubits/q3/rr/opx_output",
                "__class__": "quam_libs.components.readout_resonator.ReadoutResonatorMW"
            },
            "anharmonicity": 202800000,
            "freq_vs_flux_01_quad_term": -17790814849.333668,
            "T1": 32836,
            "T2ramsey": 2.461718327013627e-05,
            "thermalization_time_factor": 10,
            "phi0_current": 28.94330664217265,
            "phi0_voltage": 0.578866132843453,
            "chi": -375000.0,
            "grid_location": "2,0"
        },
        "q4": {
            "id": "q4",
            "xy": {
                "operations": {
                    "x180_DragCosine": {
                        "length": 16,
                        "digital_marker": "ON",
                        "axis_angle": 0,
                        "amplitude": 0.23037408505482518,
                        "alpha": -0.3554495749122419,
                        "anharmonicity": "#/qubits/q4/anharmonicity",
                        "__class__": "quam.components.pulses.DragCosinePulse"
                    },
                    "x90_DragCosine": {
                        "length": "#../x180_DragCosine/length",
                        "digital_marker": "ON",
                        "axis_angle": 0,
                        "amplitude": 0.11518704252741259,
                        "alpha": -0.034731119958269045,
                        "anharmonicity": "#../x180_DragCosine/anharmonicity",
                        "__class__": "quam.components.pulses.DragCosinePulse"
                    },
                    "-x90_DragCosine": {
                        "length": "#../x180_DragCosine/length",
                        "digital_marker": "ON",
                        "axis_angle": 3.141592653589793,
                        "amplitude": "#../x90_DragCosine/amplitude",
                        "alpha": "#../x90_DragCosine/alpha",
                        "anharmonicity": "#../x180_DragCosine/anharmonicity",
                        "detuning": "#../x180_DragCosine/detuning",
                        "__class__": "quam.components.pulses.DragCosinePulse"
                    },
                    "y180_DragCosine": {
                        "length": "#../x180_DragCosine/length",
                        "digital_marker": "ON",
                        "axis_angle": 1.5707963267948966,
                        "amplitude": "#../x180_DragCosine/amplitude",
                        "alpha": "#../x180_DragCosine/alpha",
                        "anharmonicity": "#../x180_DragCosine/anharmonicity",
                        "detuning": "#../x180_DragCosine/detuning",
                        "__class__": "quam.components.pulses.DragCosinePulse"
                    },
                    "y90_DragCosine": {
                        "length": "#../x180_DragCosine/length",
                        "digital_marker": "ON",
                        "axis_angle": 1.5707963267948966,
                        "amplitude": "#../x90_DragCosine/amplitude",
                        "alpha": "#../x90_DragCosine/alpha",
                        "anharmonicity": "#../x180_DragCosine/anharmonicity",
                        "detuning": "#../x90_DragCosine/detuning",
                        "__class__": "quam.components.pulses.DragCosinePulse"
                    },
                    "-y90_DragCosine": {
                        "length": "#../x180_DragCosine/length",
                        "digital_marker": "ON",
                        "axis_angle": -1.5707963267948966,
                        "amplitude": "#../x90_DragCosine/amplitude",
                        "alpha": "#../x90_DragCosine/alpha",
                        "anharmonicity": "#../x180_DragCosine/anharmonicity",
                        "detuning": "#../x90_DragCosine/detuning",
                        "__class__": "quam.components.pulses.DragCosinePulse"
                    },
                    "x180_Square": {
                        "length": 40,
                        "digital_marker": "ON",
                        "amplitude": 0.1,
                        "axis_angle": 0,
                        "__class__": "quam.components.pulses.SquarePulse"
                    },
                    "x90_Square": {
                        "length": "#../x180_Square/length",
                        "digital_marker": "ON",
                        "amplitude": 0.05,
                        "axis_angle": 0,
                        "__class__": "quam.components.pulses.SquarePulse"
                    },
                    "-x90_Square": {
                        "length": "#../x180_Square/length",
                        "digital_marker": "ON",
                        "amplitude": -0.125,
                        "axis_angle": 0,
                        "__class__": "quam.components.pulses.SquarePulse"
                    },
                    "y180_Square": {
                        "length": "#../x180_Square/length",
                        "digital_marker": "ON",
                        "amplitude": 0.25,
                        "axis_angle": 90,
                        "__class__": "quam.components.pulses.SquarePulse"
                    },
                    "y90_Square": {
                        "length": "#../x180_Square/length",
                        "digital_marker": "ON",
                        "amplitude": 0.125,
                        "axis_angle": 90,
                        "__class__": "quam.components.pulses.SquarePulse"
                    },
                    "-y90_Square": {
                        "length": "#../x180_Square/length",
                        "digital_marker": "ON",
                        "amplitude": -0.125,
                        "axis_angle": 90,
                        "__class__": "quam.components.pulses.SquarePulse"
                    },
                    "x180": "#./x180_DragCosine",
                    "x90": "#./x90_DragCosine",
                    "-x90": "#./-x90_DragCosine",
                    "y180": "#./y180_DragCosine",
                    "y90": "#./y90_DragCosine",
                    "-y90": "#./-y90_DragCosine",
                    "saturation": {
                        "length": 20000,
                        "digital_marker": "ON",
                        "amplitude": 0.5,
                        "axis_angle": 0,
                        "__class__": "quam.components.pulses.SquarePulse"
                    },
                    "EF_x180": {
                        "length": 16,
                        "digital_marker": "ON",
                        "axis_angle": 0,
                        "amplitude": 0.3,
                        "alpha": 0.0,
                        "anharmonicity": 150000000.0,
                        "__class__": "quam.components.pulses.DragCosinePulse"
                    }
                },
                "intermediate_frequency": -224939172.1531327,
                "thread": "d",
                "opx_output": "#/wiring/qubits/q4/xy/opx_output",
                "__class__": "quam.components.channels.MWChannel"
            },
            "z": {
                "operations": {
                    "const": {
                        "length": 100,
                        "amplitude": 0.1,
                        "__class__": "quam.components.pulses.SquarePulse"
                    }
                },
                "opx_output": "#/wiring/qubits/q4/z/opx_output",
                "independent_offset": 0.10169531433294583
            },
            "resonator": {
                "depletion_time": 1000,
                "confusion_matrix": [
                    [
                        0.959,
                        0.041
                    ],
                    [
                        0.1825,
                        0.8175
                    ]
                ],
                "operations": {
                    "readout": {
                        "length": 2000,
                        "amplitude": 0.11112322273735684,
                        "threshold": 9.053834425741879e-05,
                        "rus_exit_threshold": 1.8382008140488583e-05,
                        "integration_weights_angle": -14.61282361007536,
                        "__class__": "quam.components.pulses.SquareReadoutPulse"
                    },
                    "const": {
                        "length": 100,
                        "amplitude": 0.125,
                        "__class__": "quam.components.pulses.SquarePulse"
                    }
                },
                "intermediate_frequency": 129085329.0,
                "thread": "d",
                "opx_input": "#/wiring/qubits/q4/rr/opx_input",
                "time_of_flight": 28,
                "opx_output": "#/wiring/qubits/q4/rr/opx_output",
                "__class__": "quam_libs.components.readout_resonator.ReadoutResonatorMW"
            },
            "anharmonicity": 213200000,
            "freq_vs_flux_01_quad_term": -16116841076.835651,
            "T1": 27780,
            "T2ramsey": 2.461718327013627e-05,
            "thermalization_time_factor": 10,
            "phi0_current": 32.142058841352544,
            "phi0_voltage": 0.6428411768270509,
            "chi": -1200000.0,
            "grid_location": "3,0"
        },
        "q5": {
            "id": "q5",
            "xy": {
                "operations": {
                    "x180_DragCosine": {
                        "length": 16,
                        "digital_marker": "ON",
                        "axis_angle": 0,
                        "amplitude": 0.1725182965236667,
                        "alpha": -0.793604400137943,
                        "anharmonicity": "#/qubits/q5/anharmonicity",
                        "detuning": -3240000.0,
                        "__class__": "quam.components.pulses.DragCosinePulse"
                    },
                    "x90_DragCosine": {
                        "length": "#../x180_DragCosine/length",
                        "digital_marker": "ON",
                        "axis_angle": 0,
                        "amplitude": 0.08625914826183335,
                        "alpha": -0.6533073728094025,
                        "anharmonicity": "#../x180_DragCosine/anharmonicity",
                        "__class__": "quam.components.pulses.DragCosinePulse"
                    },
                    "-x90_DragCosine": {
                        "length": "#../x180_DragCosine/length",
                        "digital_marker": "ON",
                        "axis_angle": 3.141592653589793,
                        "amplitude": "#../x90_DragCosine/amplitude",
                        "alpha": "#../x90_DragCosine/alpha",
                        "anharmonicity": "#../x180_DragCosine/anharmonicity",
                        "detuning": "#../x180_DragCosine/detuning",
                        "__class__": "quam.components.pulses.DragCosinePulse"
                    },
                    "y180_DragCosine": {
                        "length": "#../x180_DragCosine/length",
                        "digital_marker": "ON",
                        "axis_angle": 1.5707963267948966,
                        "amplitude": "#../x180_DragCosine/amplitude",
                        "alpha": "#../x180_DragCosine/alpha",
                        "anharmonicity": "#../x180_DragCosine/anharmonicity",
                        "detuning": "#../x180_DragCosine/detuning",
                        "__class__": "quam.components.pulses.DragCosinePulse"
                    },
                    "y90_DragCosine": {
                        "length": "#../x180_DragCosine/length",
                        "digital_marker": "ON",
                        "axis_angle": 1.5707963267948966,
                        "amplitude": "#../x90_DragCosine/amplitude",
                        "alpha": "#../x90_DragCosine/alpha",
                        "anharmonicity": "#../x180_DragCosine/anharmonicity",
                        "detuning": "#../x90_DragCosine/detuning",
                        "__class__": "quam.components.pulses.DragCosinePulse"
                    },
                    "-y90_DragCosine": {
                        "length": "#../x180_DragCosine/length",
                        "digital_marker": "ON",
                        "axis_angle": -1.5707963267948966,
                        "amplitude": "#../x90_DragCosine/amplitude",
                        "alpha": "#../x90_DragCosine/alpha",
                        "anharmonicity": "#../x180_DragCosine/anharmonicity",
                        "detuning": "#../x90_DragCosine/detuning",
                        "__class__": "quam.components.pulses.DragCosinePulse"
                    },
                    "x180_Square": {
                        "length": 40,
                        "digital_marker": "ON",
                        "amplitude": 0.1,
                        "axis_angle": 0,
                        "__class__": "quam.components.pulses.SquarePulse"
                    },
                    "x90_Square": {
                        "length": "#../x180_Square/length",
                        "digital_marker": "ON",
                        "amplitude": 0.05,
                        "axis_angle": 0,
                        "__class__": "quam.components.pulses.SquarePulse"
                    },
                    "-x90_Square": {
                        "length": "#../x180_Square/length",
                        "digital_marker": "ON",
                        "amplitude": -0.125,
                        "axis_angle": 0,
                        "__class__": "quam.components.pulses.SquarePulse"
                    },
                    "y180_Square": {
                        "length": "#../x180_Square/length",
                        "digital_marker": "ON",
                        "amplitude": 0.25,
                        "axis_angle": 90,
                        "__class__": "quam.components.pulses.SquarePulse"
                    },
                    "y90_Square": {
                        "length": "#../x180_Square/length",
                        "digital_marker": "ON",
                        "amplitude": 0.125,
                        "axis_angle": 90,
                        "__class__": "quam.components.pulses.SquarePulse"
                    },
                    "-y90_Square": {
                        "length": "#../x180_Square/length",
                        "digital_marker": "ON",
                        "amplitude": -0.125,
                        "axis_angle": 90,
                        "__class__": "quam.components.pulses.SquarePulse"
                    },
                    "x180": "#./x180_DragCosine",
                    "x90": "#./x90_DragCosine",
                    "-x90": "#./-x90_DragCosine",
                    "y180": "#./y180_DragCosine",
                    "y90": "#./y90_DragCosine",
                    "-y90": "#./-y90_DragCosine",
                    "saturation": {
                        "length": 20000,
                        "digital_marker": "ON",
                        "amplitude": 0.5,
                        "axis_angle": 0,
                        "__class__": "quam.components.pulses.SquarePulse"
                    },
                    "EF_x180": {
                        "length": 16,
                        "digital_marker": "ON",
                        "axis_angle": 0,
                        "amplitude": 0.09181083125226845,
                        "alpha": 0.0,
                        "anharmonicity": 215000000,
                        "__class__": "quam.components.pulses.DragCosinePulse"
                    }
                },
                "intermediate_frequency": -20376556.26164495,
                "thread": "e",
                "opx_output": "#/wiring/qubits/q5/xy/opx_output",
                "__class__": "quam.components.channels.MWChannel"
            },
            "z": {
                "operations": {
                    "const": {
                        "length": 100,
                        "amplitude": 0.1,
                        "__class__": "quam.components.pulses.SquarePulse"
                    }
                },
                "opx_output": "#/wiring/qubits/q5/z/opx_output",
                "independent_offset": 0.027989743029789568
            },
            "resonator": {
                "depletion_time": 1000,
                "confusion_matrix": [
                    [
                        0.9675,
                        0.0325
                    ],
                    [
                        0.07,
                        0.93
                    ]
                ],
                "operations": {
                    "readout": {
                        "length": 2000,
                        "amplitude": 0.13319742900235543,
                        "threshold": -0.00020239014805913122,
                        "rus_exit_threshold": -0.0003560854552026573,
                        "integration_weights_angle": -5.222979645800339,
                        "__class__": "quam.components.pulses.SquareReadoutPulse"
                    },
                    "const": {
                        "length": 100,
                        "amplitude": 0.125,
                        "__class__": "quam.components.pulses.SquarePulse"
                    }
                },
                "intermediate_frequency": 19264454.0,
                "thread": "e",
                "opx_input": "#/wiring/qubits/q5/rr/opx_input",
                "time_of_flight": 28,
                "opx_output": "#/wiring/qubits/q5/rr/opx_output",
                "__class__": "quam_libs.components.readout_resonator.ReadoutResonatorMW"
            },
            "anharmonicity": 210600000,
            "freq_vs_flux_01_quad_term": -15724226144.297281,
            "T1": 43780,
            "T2ramsey": 2.461718327013627e-05,
            "thermalization_time_factor": 10,
            "phi0_current": 29.970596022051637,
            "phi0_voltage": 0.5994119204410328,
            "chi": -1725000.0,
            "grid_location": "4,0"
        }
    },
    "qubit_pairs": {
        "coupler_q1_q2": {
            "id": "coupler_q1_q2",
            "qubit_control": "#/wiring/qubit_pairs/q1-2/c/control_qubit",
            "qubit_target": "#/wiring/qubit_pairs/q1-2/c/target_qubit",
            "coupler": {
                "operations": {
                    "const": {
                        "length": 100,
                        "amplitude": 0.1,
                        "__class__": "quam.components.pulses.SquarePulse"
                    }
                },
                "id": "coupler_q1_q2",
                "opx_output": "#/wiring/qubit_pairs/q1-2/c/opx_output"
            }
        },
        "coupler_q2_q3": {
            "id": "coupler_q2_q3",
            "qubit_control": "#/wiring/qubit_pairs/q2-3/c/control_qubit",
            "qubit_target": "#/wiring/qubit_pairs/q2-3/c/target_qubit",
            "coupler": {
                "operations": {
                    "const": {
                        "length": 100,
                        "amplitude": 0.1,
                        "__class__": "quam.components.pulses.SquarePulse"
                    }
                },
                "id": "coupler_q2_q3",
                "opx_output": "#/wiring/qubit_pairs/q2-3/c/opx_output"
            }
        },
        "coupler_q3_q4": {
            "id": "coupler_q3_q4",
            "qubit_control": "#/wiring/qubit_pairs/q3-4/c/control_qubit",
            "qubit_target": "#/wiring/qubit_pairs/q3-4/c/target_qubit",
            "coupler": {
                "operations": {
                    "const": {
                        "length": 100,
                        "amplitude": 0.1,
                        "__class__": "quam.components.pulses.SquarePulse"
                    }
                },
                "id": "coupler_q3_q4",
                "opx_output": "#/wiring/qubit_pairs/q3-4/c/opx_output"
            }
        },
        "coupler_q4_q5": {
            "id": "coupler_q4_q5",
            "qubit_control": "#/wiring/qubit_pairs/q4-5/c/control_qubit",
            "qubit_target": "#/wiring/qubit_pairs/q4-5/c/target_qubit",
            "coupler": {
                "operations": {
                    "const": {
                        "length": 100,
                        "amplitude": 0.1,
                        "__class__": "quam.components.pulses.SquarePulse"
                    }
                },
                "id": "coupler_q4_q5",
                "opx_output": "#/wiring/qubit_pairs/q4-5/c/opx_output"
            }
        }
    },
    "active_qubit_names": [
        "q1",
        "q2",
        "q3",
        "q4",
        "q5"
    ],
    "active_qubit_pair_names": [
        "coupler_q1_q2",
        "coupler_q2_q3",
        "coupler_q3_q4",
        "coupler_q4_q5"
    ],
    "ports": {
        "analog_outputs": {
            "con1": {
                "2": {
                    "1": {
                        "controller_id": "con1",
                        "fem_id": 2,
                        "port_id": 1,
                        "delay": 172,
                        "upsampling_mode": "pulse",
                        "output_mode": "amplified",
                        "__class__": "quam.components.ports.analog_outputs.LFFEMAnalogOutputPort"
                    }
                },
                "1": {
                    "1": {
                        "controller_id": "con1",
                        "fem_id": 1,
                        "port_id": 1,
                        "delay": 172,
                        "upsampling_mode": "pulse",
                        "output_mode": "amplified",
                        "__class__": "quam.components.ports.analog_outputs.LFFEMAnalogOutputPort"
                    },
                    "2": {
                        "controller_id": "con1",
                        "fem_id": 1,
                        "port_id": 2,
                        "delay": 172,
                        "upsampling_mode": "pulse",
                        "output_mode": "amplified",
                        "__class__": "quam.components.ports.analog_outputs.LFFEMAnalogOutputPort"
                    },
                    "3": {
                        "controller_id": "con1",
                        "fem_id": 1,
                        "port_id": 3,
                        "delay": 172,
                        "upsampling_mode": "pulse",
                        "output_mode": "amplified",
                        "__class__": "quam.components.ports.analog_outputs.LFFEMAnalogOutputPort"
                    },
                    "4": {
                        "controller_id": "con1",
                        "fem_id": 1,
                        "port_id": 4,
                        "delay": 172,
                        "upsampling_mode": "pulse",
                        "output_mode": "amplified",
                        "__class__": "quam.components.ports.analog_outputs.LFFEMAnalogOutputPort"
                    },
                    "5": {
                        "controller_id": "con1",
                        "fem_id": 1,
                        "port_id": 5,
                        "delay": 172,
                        "upsampling_mode": "pulse",
                        "output_mode": "amplified",
                        "__class__": "quam.components.ports.analog_outputs.LFFEMAnalogOutputPort"
                    },
                    "6": {
                        "controller_id": "con1",
                        "fem_id": 1,
                        "port_id": 6,
                        "delay": 172,
                        "upsampling_mode": "pulse",
                        "output_mode": "amplified",
                        "__class__": "quam.components.ports.analog_outputs.LFFEMAnalogOutputPort"
                    },
                    "7": {
                        "controller_id": "con1",
                        "fem_id": 1,
                        "port_id": 7,
                        "delay": 172,
                        "upsampling_mode": "pulse",
                        "output_mode": "amplified",
                        "__class__": "quam.components.ports.analog_outputs.LFFEMAnalogOutputPort"
                    },
                    "8": {
                        "controller_id": "con1",
                        "fem_id": 1,
                        "port_id": 8,
                        "delay": 172,
                        "upsampling_mode": "pulse",
                        "output_mode": "amplified",
                        "__class__": "quam.components.ports.analog_outputs.LFFEMAnalogOutputPort"
                    }
                }
            }
        },
        "mw_outputs": {
            "con1": {
                "6": {
                    "1": {
                        "controller_id": "con1",
                        "fem_id": 6,
                        "port_id": 1,
                        "band": 2,
                        "upconverter_frequency": 5950000000,
                        "full_scale_power_dbm": -14,
                        "__class__": "quam.components.ports.analog_outputs.MWFEMAnalogOutputPort"
                    },
                    "2": {
                        "controller_id": "con1",
                        "fem_id": 6,
                        "port_id": 2,
                        "band": 1,
                        "upconverter_frequency": 4900000000.0,
                        "delay": 20,
                        "full_scale_power_dbm": 4,
                        "__class__": "quam.components.ports.analog_outputs.MWFEMAnalogOutputPort"
                    },
                    "3": {
                        "controller_id": "con1",
                        "fem_id": 6,
                        "port_id": 3,
                        "band": 1,
                        "upconverter_frequency": 4900000000.0,
                        "delay": 20,
                        "full_scale_power_dbm": 4,
                        "__class__": "quam.components.ports.analog_outputs.MWFEMAnalogOutputPort"
                    },
                    "4": {
                        "controller_id": "con1",
                        "fem_id": 6,
                        "port_id": 4,
                        "band": 1,
                        "upconverter_frequency": 4900000000.0,
                        "delay": 20,
                        "full_scale_power_dbm": 4,
                        "__class__": "quam.components.ports.analog_outputs.MWFEMAnalogOutputPort"
                    },
                    "5": {
                        "controller_id": "con1",
                        "fem_id": 6,
                        "port_id": 5,
                        "band": 1,
                        "upconverter_frequency": 4900000000.0,
                        "delay": 20,
                        "full_scale_power_dbm": 4,
                        "__class__": "quam.components.ports.analog_outputs.MWFEMAnalogOutputPort"
                    },
                    "6": {
                        "controller_id": "con1",
                        "fem_id": 6,
                        "port_id": 6,
                        "band": 1,
                        "upconverter_frequency": 4900000000.0,
                        "delay": 20,
                        "full_scale_power_dbm": 4,
                        "__class__": "quam.components.ports.analog_outputs.MWFEMAnalogOutputPort"
                    }
                }
            }
        },
        "mw_inputs": {
            "con1": {
                "6": {
                    "1": {
                        "controller_id": "con1",
                        "fem_id": 6,
                        "port_id": 1,
                        "band": 2,
                        "downconverter_frequency": 5950000000,
                        "__class__": "quam.components.ports.analog_inputs.MWFEMAnalogInputPort"
                    }
                }
            }
        }
    },
    "__class__": "quam_libs.components.quam_root.FEMQuAM"
}